autocti/__init__.py
autocti/exc.py
autocti/fixtures.py
autocti/mock.py
autocti/preloads.py
autocti/aggregator/__init__.py
autocti/aggregator/abstract.py
autocti/aggregator/cti.py
autocti/aggregator/dataset_1d.py
autocti/aggregator/fit_dataset_1d.py
autocti/aggregator/fit_imaging_ci.py
autocti/aggregator/imaging_ci.py
autocti/charge_injection/__init__.py
autocti/charge_injection/ci_util.py
autocti/charge_injection/fit.py
autocti/charge_injection/hyper.py
autocti/charge_injection/layout.py
autocti/charge_injection/master.py
autocti/charge_injection/ou_sim_ci.py
autocti/charge_injection/imaging/__init__.py
autocti/charge_injection/imaging/imaging.py
autocti/charge_injection/imaging/readout_persistence.py
autocti/charge_injection/imaging/settings.py
autocti/charge_injection/imaging/simulator.py
autocti/charge_injection/mock/__init__.py
autocti/charge_injection/mock/mock_result.py
autocti/charge_injection/model/__init__.py
autocti/charge_injection/model/analysis.py
autocti/charge_injection/model/plotter_interface.py
autocti/charge_injection/model/result.py
autocti/charge_injection/model/visualizer.py
autocti/charge_injection/plot/__init__.py
autocti/charge_injection/plot/fit_ci_plotters.py
autocti/charge_injection/plot/imaging_ci_plotters.py
autocti/clocker/__init__.py
autocti/clocker/abstract.py
autocti/clocker/one_d.py
autocti/clocker/two_d.py
autocti/config/general.yaml
autocti/config/notation.yaml
autocti/config/visualize.yaml
autocti/config/priors/ccd.yaml
autocti/config/priors/hyper.yaml
autocti/config/priors/traps.yaml
autocti/cosmics/__init__.py
autocti/cosmics/cosmics.py
autocti/cosmics/cr_distances.py
autocti/cosmics/cr_lengths.py
autocti/dataset_1d/__init__.py
autocti/dataset_1d/fit.py
autocti/dataset_1d/dataset_1d/__init__.py
autocti/dataset_1d/dataset_1d/dataset_1d.py
autocti/dataset_1d/dataset_1d/simulator.py
autocti/dataset_1d/model/__init__.py
autocti/dataset_1d/model/analysis.py
autocti/dataset_1d/model/plotter_interface.py
autocti-2024.11.13.2.dist-info/LICENSE
autocti-2024.11.13.2.dist-info/METADATA
autocti-2024.11.13.2.dist-info/WHEEL
autocti-2024.11.13.2.dist-info/top_level.txt
autocti-2024.11.13.2.dist-info/RECORD
