Metadata-Version: 2.1
Name: autocti
Version: 2024.11.13.2
Summary: PyAutoCTI: Charge Transfer Inefficiency Modeling
Home-page: https://github.com/jammy2211/PyAutoCTI
Author: James Nightingale, Richard Massey, Jacob Kegerreis and Richard Hayes
Author-email: james.w.nightingale@durham.ac.uk
License: MIT License
Keywords: cli
Classifier: Intended Audience :: Science/Research
Classifier: Topic :: Scientific/Engineering :: Physics
Classifier: License :: OSI Approved :: MIT License
Classifier: Natural Language :: English
Classifier: Operating System :: OS Independent
Classifier: Programming Language :: Python :: 3.9
Classifier: Programming Language :: Python :: 3.10
Requires-Python: >=3.7
License-File: LICENSE
Requires-Dist: nautilus-sampler ==1.0.4
Requires-Dist: autoconf ==2024.11.13.2
Requires-Dist: autofit ==2024.11.13.2
Requires-Dist: autoarray ==2024.11.13.2
